MANIFEST.in
README.md
setup.py
mlmmapi/__init__.py
mlmmapi/actors.csv
mlmmapi/names_medium_lstm.joblib
mlmmapi/predict_actor.py
mlmmapi/predict_actor.xgb
mlmmapi.egg-info/PKG-INFO
mlmmapi.egg-info/SOURCES.txt
mlmmapi.egg-info/dependency_links.txt
mlmmapi.egg-info/not-zip-safe
mlmmapi.egg-info/top_level.txt