Metadata-Version: 2.1
Name: mlmmapi
Version: 0.0.7
Summary: Tools to support the grading of short answer questions using machine learning
Home-page: https://github.com/pypa/sampleproject
Author: Daniel Brandt
Author-email: dbbrandt@gmail.com
License: UNKNOWN
Platform: UNKNOWN
Classifier: Programming Language :: Python :: 3
Classifier: License :: OSI Approved :: MIT License
Classifier: Operating System :: OS Independent
